LICENSE
README.md
TRADEMARKS.md
setup.py
lib/subfork/__init__.py
lib/subfork/app.py
lib/subfork/build.py
lib/subfork/cli.py
lib/subfork/client.py
lib/subfork/config.py
lib/subfork/deploy.py
lib/subfork/logger.py
lib/subfork/minify.py
lib/subfork/sample.py
lib/subfork/threads.py
lib/subfork/util.py
lib/subfork/version.py
lib/subfork/worker.py
lib/subfork.egg-info/PKG-INFO
lib/subfork.egg-info/SOURCES.txt
lib/subfork.egg-info/dependency_links.txt
lib/subfork.egg-info/entry_points.txt
lib/subfork.egg-info/not-zip-safe
lib/subfork.egg-info/requires.txt
lib/subfork.egg-info/top_level.txt
lib/subfork/api/__init__.py
lib/subfork/api/base.py
lib/subfork/api/data.py
lib/subfork/api/page.py
lib/subfork/api/site.py
lib/subfork/api/task.py
lib/subfork/api/user.py