Metadata-Version: 2.1
Name: subfork
Version: 1.0.3
Summary: Subfork Python API
Home-page: https://github.com/subforkdev/subfork
Author: Subfork
Author-email: help@subfork.com
License: BSD-3-Clause
Project-URL: Documentation, https://docs.fork.io
Project-URL: Demo, https://test.fork.io
Project-URL: Issue Tracker, https://github.com/subforkdev/subfork/issues
Project-URL: Trademark Policy, https://github.com/subforkdev/subfork/blob/main/TRADEMARKS.md
Classifier: Development Status :: 4 - Beta
Classifier: Intended Audience :: Developers
Classifier: Topic :: Software Development :: Libraries
Classifier: License :: OSI Approved :: BSD License
Classifier: Programming Language :: Python :: 3
Classifier: Programming Language :: Python :: 3.6
Classifier: Programming Language :: Python :: 3.7
Classifier: Programming Language :: Python :: 3.8
Classifier: Programming Language :: Python :: 3.9
Classifier: Programming Language :: Python :: 3.10
Classifier: Programming Language :: Python :: 3.11
Requires-Python: >=3.6
License-File: LICENSE
License-File: TRADEMARKS.md
Requires-Dist: jsmin>=3.0.1
Requires-Dist: psutil>=5.9.3
Requires-Dist: PyYAML>=5.4
Requires-Dist: requests>=2.25.1
Requires-Dist: urllib3>=1.26.2
Requires-Dist: python-socketio~=5.11
Requires-Dist: websocket-client<2,>=1.6
